{
	"configurations" : 
	[
		{
			"directories" : 
			[
				{
					"build" : ".",
					"hasInstallRule" : true,
					"jsonFile" : "directory-.-Release-5df109238cce02536e85.json",
					"minimumCMakeVersion" : 
					{
						"string" : "3.16"
					},
					"projectIndex" : 0,
					"source" : ".",
					"targetIndexes" : 
					[
						0,
						1,
						2,
						3,
						4,
						5,
						6,
						7,
						8,
						9,
						10,
						11,
						12,
						13,
						14,
						15
					]
				}
			],
			"name" : "Release",
			"projects" : 
			[
				{
					"directoryIndexes" : 
					[
						0
					],
					"name" : "ratatouile",
					"targetIndexes" : 
					[
						0,
						1,
						2,
						3,
						4,
						5,
						6,
						7,
						8,
						9,
						10,
						11,
						12,
						13,
						14,
						15
					]
				}
			],
			"targets" : 
			[
				{
					"directoryIndex" : 0,
					"id" : "Felgo_other_files::@6890427a1f51a3e7e1df",
					"jsonFile" : "target-Felgo_other_files-Release-c8b80156ddd834403c19.json",
					"name" : "Felgo_other_files",
					"projectIndex" : 0
				},
				{
					"directoryIndex" : 0,
					"id" : "Felgo_resources_1::@6890427a1f51a3e7e1df",
					"jsonFile" : "target-Felgo_resources_1-Release-308c6eb72ee33a71742f.json",
					"name" : "Felgo_resources_1",
					"projectIndex" : 0
				},
				{
					"directoryIndex" : 0,
					"id" : "Felgo_resources_1_autogen::@6890427a1f51a3e7e1df",
					"jsonFile" : "target-Felgo_resources_1_autogen-Release-adbff8a05c31cec7bf9d.json",
					"name" : "Felgo_resources_1_autogen",
					"projectIndex" : 0
				},
				{
					"directoryIndex" : 0,
					"id" : "Felgo_resources_1_autogen_timestamp_deps::@6890427a1f51a3e7e1df",
					"jsonFile" : "target-Felgo_resources_1_autogen_timestamp_deps-Release-8180fbfb468972fbbbc1.json",
					"name" : "Felgo_resources_1_autogen_timestamp_deps",
					"projectIndex" : 0
				},
				{
					"directoryIndex" : 0,
					"id" : "all_qmllint::@6890427a1f51a3e7e1df",
					"jsonFile" : "target-all_qmllint-Release-3fc4882b596b03ba58a9.json",
					"name" : "all_qmllint",
					"projectIndex" : 0
				},
				{
					"directoryIndex" : 0,
					"id" : "all_qmllint_json::@6890427a1f51a3e7e1df",
					"jsonFile" : "target-all_qmllint_json-Release-68c8c62308a477b29f6f.json",
					"name" : "all_qmllint_json",
					"projectIndex" : 0
				},
				{
					"directoryIndex" : 0,
					"id" : "all_qmltyperegistrations::@6890427a1f51a3e7e1df",
					"jsonFile" : "target-all_qmltyperegistrations-Release-c4a81854d3e7ce783246.json",
					"name" : "all_qmltyperegistrations",
					"projectIndex" : 0
				},
				{
					"directoryIndex" : 0,
					"id" : "appratatouile::@6890427a1f51a3e7e1df",
					"jsonFile" : "target-appratatouile-Release-77b0c180e6ef05ee5cf5.json",
					"name" : "appratatouile",
					"projectIndex" : 0
				},
				{
					"directoryIndex" : 0,
					"id" : "appratatouile_autogen::@6890427a1f51a3e7e1df",
					"jsonFile" : "target-appratatouile_autogen-Release-dfe6e3220347afd95b3f.json",
					"name" : "appratatouile_autogen",
					"projectIndex" : 0
				},
				{
					"directoryIndex" : 0,
					"id" : "appratatouile_autogen_timestamp_deps::@6890427a1f51a3e7e1df",
					"jsonFile" : "target-appratatouile_autogen_timestamp_deps-Release-8f607d849f4466412df7.json",
					"name" : "appratatouile_autogen_timestamp_deps",
					"projectIndex" : 0
				},
				{
					"directoryIndex" : 0,
					"id" : "appratatouile_other_files::@6890427a1f51a3e7e1df",
					"jsonFile" : "target-appratatouile_other_files-Release-4debb66654edfcb55d01.json",
					"name" : "appratatouile_other_files",
					"projectIndex" : 0
				},
				{
					"directoryIndex" : 0,
					"id" : "appratatouile_qmlimportscan::@6890427a1f51a3e7e1df",
					"jsonFile" : "target-appratatouile_qmlimportscan-Release-c37a46210ce88ae11ae9.json",
					"name" : "appratatouile_qmlimportscan",
					"projectIndex" : 0
				},
				{
					"directoryIndex" : 0,
					"id" : "appratatouile_qmllint::@6890427a1f51a3e7e1df",
					"jsonFile" : "target-appratatouile_qmllint-Release-ce8356c3fb3a079d9f3d.json",
					"name" : "appratatouile_qmllint",
					"projectIndex" : 0
				},
				{
					"directoryIndex" : 0,
					"id" : "appratatouile_qmllint_json::@6890427a1f51a3e7e1df",
					"jsonFile" : "target-appratatouile_qmllint_json-Release-24da6b43f69d944c7b55.json",
					"name" : "appratatouile_qmllint_json",
					"projectIndex" : 0
				},
				{
					"directoryIndex" : 0,
					"id" : "appratatouile_qmltyperegistration::@6890427a1f51a3e7e1df",
					"jsonFile" : "target-appratatouile_qmltyperegistration-Release-451acf08b04b584799ff.json",
					"name" : "appratatouile_qmltyperegistration",
					"projectIndex" : 0
				},
				{
					"directoryIndex" : 0,
					"id" : "appratatouile_tooling::@6890427a1f51a3e7e1df",
					"jsonFile" : "target-appratatouile_tooling-Release-d413da0678b5660f07c3.json",
					"name" : "appratatouile_tooling",
					"projectIndex" : 0
				}
			]
		}
	],
	"kind" : "codemodel",
	"paths" : 
	{
		"build" : "F:/programas/git/ratatouille/Game_Log/build/Felgo_SDK_Desktop_Qt_6_4_1_MinGW_64_bit-Release",
		"source" : "F:/programas/git/ratatouille/Game_Log"
	},
	"version" : 
	{
		"major" : 2,
		"minor" : 7
	}
}
